{"is_source_file": false, "format": "", "description": "", "external_files": [], "external_methods": [], "published": [], "classes": [], "methods": [], "calls": [], "search-terms": ["simple-queue-management-system", "README.md"], "state": 2, "file_id": 1, "knowledge_revision": 9, "git_revision": "2934cffa0992512a20501f50e3e7d5b84ce97962", "hash": "a104433979290f4c262a3d20a630035f", "format-version": 4, "code-base-name": "queue_backend", "filename": "README.md", "revision_history": [{"9": "2934cffa0992512a20501f50e3e7d5b84ce97962"}]}